super_state_machine/__init__.py
super_state_machine/errors.py
super_state_machine/extras.py
super_state_machine/machines.py
super_state_machine/utils.py
super_state_machine-2.1.0.dist-info/METADATA
super_state_machine-2.1.0.dist-info/WHEEL
super_state_machine-2.1.0.dist-info/licenses/LICENSE
super_state_machine-2.1.0.dist-info/RECORD
