Metadata-Version: 2.4
Name: super_state_machine
Version: 2.1.0
Author-email: Szczepan Cieślik <szczepan.cieslik@gmail.com>
Maintainer-email: Eric Dill <eric.dill@maxpoint.com>, Thomas A Caswell <tcaswell@gmail.com>
License-Expression: MIT AND (Apache-2.0 OR BSD-2-Clause)
License-File: LICENSE
Classifier: Intended Audience :: Developers
Classifier: License :: OSI Approved :: BSD License
Classifier: Natural Language :: English
Classifier: Programming Language :: Python :: 3.9
Classifier: Programming Language :: Python :: 3.10
Classifier: Programming Language :: Python :: 3.11
Classifier: Programming Language :: Python :: 3.12
Classifier: Programming Language :: Python :: 3.13
Provides-Extra: dev
Requires-Dist: coverage; extra == 'dev'
Requires-Dist: mccabe; extra == 'dev'
Requires-Dist: pytest; extra == 'dev'
Requires-Dist: pytest-cov; extra == 'dev'
Provides-Extra: docs
Requires-Dist: sphinx; extra == 'docs'
